fastapi_config/__init__.py
fastapi_config/__pycache__/__init__.cpython-310.pyc
fastapi_config/__pycache__/__init__.cpython-311.pyc
fastapi_config/__pycache__/__init__.cpython-38.pyc
fastapi_config/__pycache__/admin.cpython-310.pyc
fastapi_config/__pycache__/admin.cpython-311.pyc
fastapi_config/__pycache__/admin.cpython-38.pyc
fastapi_config/__pycache__/backends.cpython-310.pyc
fastapi_config/__pycache__/backends.cpython-311.pyc
fastapi_config/__pycache__/backends.cpython-38.pyc
fastapi_config/__pycache__/globals.cpython-311.pyc
fastapi_config/__pycache__/models.cpython-310.pyc
fastapi_config/__pycache__/models.cpython-311.pyc
fastapi_config/__pycache__/models.cpython-38.pyc
fastapi_config/admin.py
fastapi_config/backends.py
fastapi_config/extensions/__init__.py
fastapi_config/extensions/__pycache__/__init__.cpython-311.pyc
fastapi_config/extensions/__pycache__/redis.cpython-311.pyc
fastapi_config/extensions/redis.py
fastapi_config/globals.py
fastapi_config/locale/base.pot
fastapi_config/locale/de_DE/LC_MESSAGES/messages.mo
fastapi_config/locale/de_DE/LC_MESSAGES/messages.po
fastapi_config/locale/zh_CN/LC_MESSAGES/messages.mo
fastapi_config/locale/zh_CN/LC_MESSAGES/messages.po
fastapi_config/models.py
fastapi_config-0.1.4.dist-info/WHEEL
fastapi_config-0.1.4.dist-info/METADATA
fastapi_config-0.1.4.dist-info/RECORD
