Metadata-Version: 2.1
Name: fastapi_config
Version: 0.1.4
Summary: FastAPI-Config is a visual dynamic configuration management extension based on FastAPI-Amis-Admin.
Keywords: FastAPI-Amis-Admin,FastAPI-Config,Python-Config
Author-email: Atomi <1456417373@qq.com>
Requires-Python: >=3.8
Classifier: Environment :: Web Environment
Classifier: Framework :: FastAPI
Classifier: License :: OSI Approved :: Apache Software License
Classifier: Operating System :: OS Independent
Classifier: Programming Language :: Python :: 3
Classifier: Programming Language :: Python :: 3.10
Classifier: Programming Language :: Python :: 3.11
Classifier: Programming Language :: Python :: 3.7
Classifier: Programming Language :: Python :: 3.8
Classifier: Programming Language :: Python :: 3.9
Classifier: Topic :: System :: Systems Administration
Requires-Dist: asyncer>=0.0.1
Requires-Dist: fastapi-amis-admin>=0.6.4
Requires-Dist: sqlalchemy-database>=0.1.1
Provides-Extra: demo
Requires-Dist: pydantic[email]>=1.10.1; extra == "demo"
Requires-Dist: uvicorn>=0.18.3; extra == "demo"
Provides-Extra: test
Requires-Dist: pytest>=7.1.3; extra == "test"
Requires-Dist: aiosqlite>=0.17.0; extra == "test"
Requires-Dist: pytest-asyncio>=0.19.0; extra == "test"
Project-URL: FastAPI-Amis-Admin, https://github.com/amisadmin/fastapi_amis_admin
Project-URL: Source, https://github.com/amisadmin/fastapi_config
